LICENSE
MANIFEST.in
README.md
requirements.txt
setup.py
DLCreator/__init__.py
DLCreator/command.py
DLCreator.egg-info/PKG-INFO
DLCreator.egg-info/SOURCES.txt
DLCreator.egg-info/dependency_links.txt
DLCreator.egg-info/entry_points.txt
DLCreator.egg-info/requires.txt
DLCreator.egg-info/top_level.txt
DLCreator/templates/.DS_Store
DLCreator/templates/keras/README.md
DLCreator/templates/keras/config.json
DLCreator/templates/keras/data/processed/.gitkeep
DLCreator/templates/keras/data/source/.gitkeep
DLCreator/templates/keras/data_loader/__init__.py
DLCreator/templates/keras/data_loader/data_loader.py
DLCreator/templates/keras/model/__init__.py
DLCreator/templates/keras/model/base.py
DLCreator/templates/keras/model/simple_mnist_model.py
DLCreator/templates/keras/plaground/.gitkeep
DLCreator/templates/keras/trainer/__init__.py
DLCreator/templates/keras/trainer/base.py
DLCreator/templates/keras/trainer/trainer.py
DLCreator/templates/keras/utils/__init__.py
DLCreator/templates/keras/utils/config.py
DLCreator/templates/keras/utils/log.py
DLCreator/templates/pytorch/README.md
DLCreator/templates/tensorflow/README.md
dlcreator/__init__.py
dlcreator/command.py
dlcreator/templates/.DS_Store
dlcreator/templates/keras/README.md
dlcreator/templates/keras/data_loader/__init__.py
dlcreator/templates/keras/utils/__init__.py
dlcreator/templates/keras/utils/config.py