Metadata-Version: 1.2
Name: DLCreator
Version: 0.1.7
Summary: One-line command to generate a deep learning folder structure and code template!
Home-page: https://github.com/nghuyong/DLCreator
Author: nghuyong
Author-email: nghuyong@163.com
License: MIT Licence
Keywords: deep learning,tool
Platform: any
Requires-Python: >=2.7, !=3.0.*, !=3.1.*, !=3.2.*, !=3.3.*
